py_army_days/__init__.py
py_army_days/cli.py
py_army_days/core.py
py_army_days/models.py
py_army_days/output.py
py_army_days/ansi_text/__init__.py
py_army_days-0.1.0.dist-info/METADATA
py_army_days-0.1.0.dist-info/WHEEL
py_army_days-0.1.0.dist-info/entry_points.txt
py_army_days-0.1.0.dist-info/RECORD
