Metadata-Version: 2.3
Name: py-army-days
Version: 0.1.0
Summary: Add your description here
Requires-Python: >=3.12
Requires-Dist: click>=8.1.7
Requires-Dist: pydantic>=2.9.1
Requires-Dist: pyyaml>=6.0.2
